wg_config/__init__.py
wg_config/__main__.py
wg_config/cli.py
wg_config/peer.py
wg_config/py.typed
wg_config/wireguard.py
wg_config-0.1.0.dist-info/LICENSE
wg_config-0.1.0.dist-info/METADATA
wg_config-0.1.0.dist-info/WHEEL
wg_config-0.1.0.dist-info/entry_points.txt
wg_config-0.1.0.dist-info/RECORD
