Metadata-Version: 2.1
Name: wg-config
Version: 0.1.0
Summary: 
Author: Nima Roomi
Author-email: nimar@firehousealerting.com
Requires-Python: >=3.8,<4.0
Classifier: Programming Language :: Python :: 3
Classifier: Programming Language :: Python :: 3.8
Classifier: Programming Language :: Python :: 3.9
Classifier: Programming Language :: Python :: 3.10
Classifier: Programming Language :: Python :: 3.11
Classifier: Programming Language :: Python :: 3.12
Requires-Dist: rich (>=13.5.3,<14.0.0)
Requires-Dist: typer (>=0.9.0,<0.10.0)
Requires-Dist: wgconfig (>=1.0.0,<2.0.0)
